{
  "id": "e5da5a1d-abf3-4d9d-8ecd-3173d138f872",
  "title": "তার নাম FANT ৷",
  "slug": "tar-nam",
  "content": "রাজা কাঞ্চনকান্তির আছে একটি কন্যা ৷\n\nকাঞ্চনকান্তি 1\n\nসেই  দেশের নাম ۱\n\nদেশটির আর  সেই  রাজাটির নামটি হল\n\nএক  যে  ছিলেন রাজা |\n\nবরযাত্রী\n\nসহকারী\n\nযথাসময়ে\n\nজমকেই\n\nঘোড়া,\n\nঘোড়াশালে\n\nহাতী,\n\nহাতীশালে\n\nহলো\n\nসাজানো\n\nরাজবাড়ী\n\nসপ্তাহ\n\nহৈ-চৈ\n\nআর\n\nরাজা,\n\nরাজ্যে\n\nধরে।\n\nFTF\n\nFS\n৷\n\nও\nকাড়ানাকড়া।\n\nat\n\n\nT\nWea\n|!\n[|\n\n111 ly",
  "source_book": "Tkakurmar Jhuli",
  "language": "bn",
  "pages": [
    19
  ],
  "status": "raw",
  "checksum": "b6982ee02e4e0f30d8b2502de95899faba9d2e32b213cb4cc704fdee1ea09471"
}